cpref/__init__.py
cpref/exc.py
cpref/object_ref.py
cpref_test/__init__.py
cpref_test/object_ref.py
cpref-1.1.1.dist-info/LICENSE
cpref-1.1.1.dist-info/METADATA
cpref-1.1.1.dist-info/WHEEL
cpref-1.1.1.dist-info/top_level.txt
cpref-1.1.1.dist-info/RECORD
